phasedm-1.2.1.dist-info/METADATA
phasedm-1.2.1.dist-info/WHEEL
phasedm-1.2.1.dist-info/licenses/LICENSE
phasedm/__init__.py
phasedm/phasedm.pyi
phasedm/py.typed
phasedm/phasedm.pypy39-pp73-arm-linux-gnu.so
phasedm-1.2.1.dist-info/RECORD
