Metadata-Version: 2.4
Name: phasedm
Version: 1.2.1
Classifier: Programming Language :: Rust
Classifier: Programming Language :: Python :: Implementation :: CPython
Classifier: Programming Language :: Python :: 3.8
Classifier: Programming Language :: Python :: 3.9
Classifier: Programming Language :: Python :: 3.10
Classifier: Programming Language :: Python :: 3.11
Classifier: Programming Language :: Python :: 3.12
Requires-Dist: pytest ; extra == 'tests'
Provides-Extra: tests
License-File: LICENSE
Requires-Python: >=3.8, <3.13
